pysdk_sui
